{"type": "Feature", "id": 12514809, "properties": {"woe:id": 12514809, "woe:parent_id": 2268089, "woe:name": "Khasab Airport", "woe:placetype": 14, "woe:placetype_name": "Airport", "woe:lang": "ENG", "iso:country": "OM", "meta:provider": ["geoplanet:7.3.1", "geoplanet:7.3.2", "geoplanet:7.4.0", "geoplanet:7.4.1", "geoplanet:7.5.1", "geoplanet:7.5.2", "geoplanet:7.6.0", "geoplanet:7.8.1", "geoplanet:7.9.0", "geoplanet:7.10.0", "geoplanet:8.0.0", "woeplanet:8.0.0"], "meta:indexed": "2020-08-20T21:02:18.801209", "woe:alias_ENG_V": ["KHS Airport", "KHS"], "meta:updated": "2020-08-22T02:58:58.046187", "woe:hierarchy": {"continent": 24865671, "country": 23424898, "town": 0, "planet": 1, "county": 55927050, "suburb": 0, "state": 4693371, "region": 0, "localadmin": 0}, "woe:timezone_id": 28350844, "woe:hash": "thxuzdvpq9t3", "woe:centroid": [56.23518, 26.16382], "geom:latitude": 26.16382, "geom:longitude": 56.23518, "geom:hash": "thxuzdvpq9t3", "woe:latitude": 26.16382, "geom:centroid": [56.23518, 26.16382], "woe:longitude": 56.23518, "woe:repo": "woeplanet-airport-om"}, "geometry": {"coordinates": [56.23518, 26.16382], "type": "Point"}}